MANIFEST.in
README.md
setup.py
paratureapiclient/__init__.py
paratureapiclient/exceptions.py
paratureapiclient/parature.py
paratureapiclient/resource.py
paratureapiclient/response.py
paratureapiclient.egg-info/PKG-INFO
paratureapiclient.egg-info/SOURCES.txt
paratureapiclient.egg-info/dependency_links.txt
paratureapiclient.egg-info/not-zip-safe
paratureapiclient.egg-info/requires.txt
paratureapiclient.egg-info/top_level.txt