Metadata-Version: 1.0
Name: paratureapiclient
Version: 0.50
Summary: Wrapper for working with the Parature RESTful API
Home-page: https://github.com/joelcolucci/paratureapiclient
Author: Joel Colucci
Author-email: joelcolucci@gmail.com
License: MIT
Platform: UNKNOWN
